{
  "event_id": "RXZlbnRfMTM3MjY5Nw==",
  "stats_total_leads": 10169,
  "stats_badges_scanned": 0,
  "stats_business_cards_scanned": 3,
  "stats_connections_made": 776,
  "stats_connection_requests_sent": 56,
  "stats_messages_exchanged": 1143,
  "stats_meetings_created": 0,
  "stats_exhibitor_views": 9330,
  "stats_exhibitor_bookmarks": 60,
  "event_breakdown": {
    "product_show": 5019,
    "event_start": 4357,
    "event_show": 6117,
    "event_advertisement_show": 2523,
    "event_view_show": 8917,
    "exhibitor_show": 9330,
    "exhibitors_view_filter": 1043,
    "person_show": 1252,
    "connection_request_create": 56,
    "message_create": 1143,
    "planning_bookmark_create": 23,
    "planning_stream_start": 26,
    "planning_stream_stop": 26,
    "sponsor_show": 879,
    "event_advertisement_open": 172,
    "exhibitors_view_search": 738,
    "people_view_search": 327,
    "products_view_search": 138,
    "products_view_filter": 116,
    "exhibitor_advertisement_show": 82,
    "plannings_view_search": 18,
    "plannings_view_filter": 14,
    "document_open": 64,
    "meeting_update": 18,
    "meeting_participant_update": 13,
    "product_bookmark_create": 70,
    "connection_update": 3536,
    "connection_request_update": 474,
    "connection_create": 776,
    "exhibitor_bookmark_create": 60,
    "people_view_filter": 98,
    "contact_connection_create": 3,
    "exhibitor_advertisement_open": 3,
    "exhibitor_self_show": 42,
    "channel_open": 1,
    "video_call_room_end": 3
  },
  "raw_count": 47477,
  "fetched_at": "2026-02-22T16:27:38.641177",
  "time_gt": "2024-02-23T13:09:13.000Z",
  "time_lt": null
}